{
  "type": "FeatureCollection",
  "crs": {
    "type": "name",
    "properties": {
      "name": "EPSG:3857"
    }
  },
  "features": [
    {
      "type": "Feature",
      "properties": {},
      "geometry": {
        "type": "Point",
        "coordinates": [
          2.175716819846508,
          41.40249350940042
        ]
      }
    }
  ]
}